{
  "UserAgent": "MobileHub/1.0",
  "Version": "1.0",
  "CredentialsProvider": {
    "CognitoIdentity": {
      "Default": {
        "PoolId": "eu-central-1:3ec63f0a-14df-41c4-81f8-802b4c73401d",
        "Region": "eu-central-1"
      }
    }
  },
  "IdentityManager": {
    "Default": {}
  },
  "S3TransferUtility": {
    "Default": {
      "Bucket": "consolegamesexchange-userfiles-mobilehub-1803474052",
      "Region": "eu-central-1"
    }
  },
  "PinpointAnalytics": {
    "Default": {
      "AppId": "c4e58d99768b44888934c217458ed244",
      "Region": "us-east-1"
    }
  },
  "PinpointTargeting": {
    "Default": {
      "Region": "us-east-1"
    }
  },
  "UserFileManager": {
    "Default": {
      "Bucket": "consolegamesexchange-userfiles-mobilehub-1803474052",
      "Region": "eu-central-1"
    }
  }
}